SNP1/__init__.py
SNP1/snp.py
SNP1-0.0.1.dist-info/License.txt
SNP1-0.0.1.dist-info/METADATA
SNP1-0.0.1.dist-info/WHEEL
SNP1-0.0.1.dist-info/top_level.txt
SNP1-0.0.1.dist-info/RECORD
