Metadata-Version: 2.1
Name: SNP1
Version: 0.0.1
Summary: Returns AP,GP sum and progression series
Author-email: Nigesh <nigeshpalani23@gmail.com>
Project-URL: Homepage, https://github.com/pypa/sampleproject
Project-URL: Bug Tracker, https://github.com/pypa/sampleproject/issues
Classifier: Programming Language :: Python :: 3
Classifier: License :: OSI Approved :: MIT License
Classifier: Operating System :: OS Independent
Requires-Python: >=3.7
License-File: License.txt
